elabftwqrprint/__init__.py
elabftwqrprint/_cli_args.py
elabftwqrprint/_elabftw_interface.py
elabftwqrprint/_global_defaults.py
elabftwqrprint/configure_elabftw.py
elabftwqrprint/configure_printer.py
elabftwqrprint/create_qr_sticker.py
elabftwqrprint/create_sticker_elab_item.py
elabftwqrprint/defaultfont.ttf
elabftwqrprint/find_items.py
elabftwqrprint/list_elab_items.py
elabftwqrprint/print_sticker.py
elabftwqrprint/print_sticker_elab_item.py
elabftwqrprint/utils.py
elabftwqrprint-0.1.0.dist-info/LICENSE
elabftwqrprint-0.1.0.dist-info/METADATA
elabftwqrprint-0.1.0.dist-info/WHEEL
elabftwqrprint-0.1.0.dist-info/entry_points.txt
elabftwqrprint-0.1.0.dist-info/top_level.txt
elabftwqrprint-0.1.0.dist-info/RECORD
