Metadata-Version: 2.1
Name: elabftwqrprint
Version: 0.1.0
Summary: Make QR code stickers for elabFTW database entries and print them with Brother label printers.
Home-page: https://github.com/din14970/elabftwqrprint
Author: Niels Cautaerts
Author-email: nielscautaerts@hotmail.com
License: GPL-3.0
Keywords: e-lab,provenance,lab management
Platform: UNKNOWN
Classifier: Topic :: Scientific/Engineering
Classifier: Intended Audience :: Science/Research
Classifier: Operating System :: OS Independent
Classifier: Programming Language :: Python :: 3.8
Requires-Dist: brother-ql (>=0.9.4)
Requires-Dist: elabapy (>=0.6.1)
Requires-Dist: pyyaml (>=5.1)
Requires-Dist: Pillow (>=7.2.0)
Requires-Dist: tabulate (>=0.8.7)
Requires-Dist: qrcode (>=6.1)
